torchanalyse/__init__.py
torchanalyse/profile.py
torchanalyse/system.py
torchanalyse/unit.py
torchanalyse/version.py
torchanalyse/utils/__init__.py
torchanalyse/utils/flatten.py
torchanalyse/utils/trace.py
torchanalyse/utils/ir/__init__.py
torchanalyse/utils/ir/graph.py
torchanalyse/utils/ir/node.py
torchanalyse/utils/ir/variable.py
torchanalyse/utils/operatorlist/__init__.py
torchanalyse/utils/operatorlist/energy_cost.py
torchanalyse/utils/operatorlist/math.py
torchanalyse/utils/operatorlist/operator_base.py
torchanalyse/utils/operatorlist/operator_list.py
torchanalyse-0.0.3.dist-info/METADATA
torchanalyse-0.0.3.dist-info/WHEEL
torchanalyse-0.0.3.dist-info/top_level.txt
torchanalyse-0.0.3.dist-info/RECORD
